Queen Successor Trigger Unit - QSTU/Queen Successor Trigger Unit - QSTU.srcs/sources_1/new/QSTU.sv
//============================================================
// Queen Succession Trigger Unit (QSTU)
//============================================================
// - Detects fast failures (event-driven)
// - Computes slow health score (periodic inputs)
// - Triggers QSSE when required
//============================================================

module QSTU (
    input  logic              clk,
    input  logic              rst_n,

    // -------------------------
    // Control
    // -------------------------
    input  logic              flight_stable,

    // -------------------------
    // Slow time-varying inputs
    // -------------------------
    input  logic [7:0]        bat_soc,          // Q0.8
    input  logic [7:0]        bat_soh,          // Q0.8
    input  logic signed [11:0] avg_temperature, // Q7.5
    input  logic [7:0]        link_quality,     // Q0.8

    // -------------------------
    // Fast time-varying inputs
    // -------------------------
    input  logic              bat_uv_flag,
    input  logic              thermal_trip,
    input  logic              comm_timeout,

    // -------------------------
    // Output
    // -------------------------
    output logic              elec_trigger
);

    //========================================================
    // PARAMETERS
    //========================================================

    // Temperature limits (Q7.5)
    localparam signed [12:0] TEMP_MIN_Q = 13'sd640;   // 20 * 2^5
    localparam signed [12:0] TEMP_MAX_Q = 13'sd2560;  // 80 * 2^5

    // Min-max scaling constants for temperature health
    // temp_health = (-1/60)*T + (80/60)
    // Q1.15 format
    localparam signed [15:0] TEMP_C1 = -16'sd546;    // -1/60
    localparam signed [15:0] TEMP_C2 =  16'sd43690;  // 80/60

    // Health score weights (Q1.15) - example values
    localparam signed [15:0] W_SOC  = 16'sd8192;  // 0.25
    localparam signed [15:0] W_SOH  = 16'sd8192;  // 0.25
    localparam signed [15:0] W_TEMP = 16'sd8192;  // 0.25
    localparam signed [15:0] W_LINK = 16'sd8192;  // 0.25

    // Red band threshold (0.3 in Q1.15)
    localparam signed [15:0] RED_BAND_THRESHOLD = 16'sd9830;

    //========================================================
    // INTERNAL SIGNALS
    //========================================================

    logic signed [11:0] clmp_temp;
    logic signed [31:0] temp_mult;
    logic signed [15:0] temp_health;

    logic signed [31:0] soc_mult, soh_mult, temp_h_mult, link_mult;
    logic signed [31:0] score_accum;
    logic signed [15:0] health_score;

    logic fast_failure;

    //========================================================
    // TEMPERATURE CLAMP
    //========================================================
    always_comb begin
        if (avg_temperature < TEMP_MIN_Q)
            clmp_temp = TEMP_MIN_Q;
        else if (avg_temperature > TEMP_MAX_Q)
            clmp_temp = TEMP_MAX_Q;
        else
            clmp_temp = avg_temperature;
    end

    //========================================================
    // TEMPERATURE HEALTH (Affine Mapping)
    //========================================================
    always_comb begin
        temp_mult   = clmp_temp * TEMP_C1;          // Q7.5 * Q1.15 → Q8.20
        temp_health = (temp_mult >>> 5) + TEMP_C2;  // Align to Q1.15

        // Saturation
        if (temp_health < 0)
            temp_health = 16'sd0;
        else if (temp_health > 16'sh7FFF)
            temp_health = 16'sh7FFF;
    end

    //========================================================
    // FAST FAILURE DETECTION
    //========================================================
    assign fast_failure = bat_uv_flag | thermal_trip | comm_timeout;

    //========================================================
    // HEALTH SCORE COMPUTATION
    //========================================================
    always_comb begin
        soc_mult    = bat_soc       * W_SOC;   // Q0.8 * Q1.15 → Q1.23
        soh_mult    = bat_soh       * W_SOH;
        temp_h_mult = temp_health  * W_TEMP;  // Q1.15 * Q1.15 → Q2.30
        link_mult   = link_quality * W_LINK;

        score_accum =
              (soc_mult    >>> 8)
            + (soh_mult    >>> 8)
            + (temp_h_mult >>> 15)
            + (link_mult   >>> 8);

        // Saturate to Q1.15
        if (score_accum < 0)
            health_score = 16'sd0;
        else if (score_accum > 16'sh7FFF)
            health_score = 16'sh7FFF;
        else
            health_score = score_accum[15:0];
    end

    //========================================================
    // TRIGGER LOGIC
    //========================================================
    always_comb begin
        if (!flight_stable)
            elec_trigger = 1'b0;
        else if (fast_failure)
            elec_trigger = 1'b1;
        else if (health_score <= RED_BAND_THRESHOLD)
            elec_trigger = 1'b1;
        else
            elec_trigger = 1'b0;
    end

endmodule

Queen Successor Trigger Unit - QSTU/Queen Successor Trigger Unit - QSTU.srcs/sim_1/new/qstu_tb.sv
`timescale 1ns/1ps
//define USE_OPT_QSTU   // Comment this line to test QSTU instead

module qstu_tb;

    // -------------------------------------------------
    // DUT Signals
    // -------------------------------------------------
    logic              clk;
    logic              rst_n;
    logic              flight_stable;

    logic [7:0]        bat_soc;
    logic [7:0]        bat_soh;
    logic signed [11:0] avg_temperature;
    logic [7:0]        link_quality;

    logic              bat_uv_flag;
    logic              thermal_trip;
    logic              comm_timeout;

    logic              elec_trigger;

    // -------------------------------------------------
    // Instantiate DUT (Selectable)
    // -------------------------------------------------
`ifdef USE_OPT_QSTU
    opt_qstu dut (
`else
    QSTU dut (
`endif
        .clk(clk),
        .rst_n(rst_n),
        .flight_stable(flight_stable),

        .bat_soc(bat_soc),
        .bat_soh(bat_soh),
        .avg_temperature(avg_temperature),
        .link_quality(link_quality),

        .bat_uv_flag(bat_uv_flag),
        .thermal_trip(thermal_trip),
        .comm_timeout(comm_timeout),

        .elec_trigger(elec_trigger)
    );

    // -------------------------------------------------
    // Clock Generation
    // -------------------------------------------------
    always #5 clk = ~clk;

    // -------------------------------------------------
    // Utility Tasks
    // -------------------------------------------------
    task reset_dut;
    begin
        clk = 0;
        rst_n = 0;
        flight_stable = 0;

        bat_soc = 0;
        bat_soh = 0;
        avg_temperature = 0;
        link_quality = 0;

        bat_uv_flag = 0;
        thermal_trip = 0;
        comm_timeout = 0;

        #20;
        rst_n = 1;
        #10;
    end
    endtask

    task show_status(string label);
    begin
        $display("[%0t] %s | TRIGGER=%0d",
                 $time, label, elec_trigger);
    end
    endtask

    // -------------------------------------------------
    // Test Sequence
    // -------------------------------------------------
    initial begin
        $display("========================================");
`ifdef USE_OPT_QSTU
        $display(" TESTING opt_qstu");
`else
        $display(" TESTING QSTU");
`endif
        $display("========================================");

        $dumpfile("simulation.vcd");
        $dumpvars(0, qstu_tb);

        reset_dut();

        // ---------------------------------------------
        // TEST 1: Flight not stable → trigger must be 0
        // ---------------------------------------------
        bat_soc = 8'd255;
        bat_soh = 8'd255;
        link_quality = 8'd255;
        avg_temperature = 12'sd1280; // 40C
        flight_stable = 0;

        #20;
        show_status("TEST1: flight_stable=0 (EXPECT 0)");

        // ---------------------------------------------
        // TEST 2: Healthy system → no trigger
        // ---------------------------------------------
        flight_stable = 1;
        bat_soc = 8'd230;
        bat_soh = 8'd240;
        link_quality = 8'd220;
        avg_temperature = 12'sd1280;

        #20;
        show_status("TEST2: healthy inputs (EXPECT 0)");

        // ---------------------------------------------
        // TEST 3: Fast failure - undervoltage
        // ---------------------------------------------
        bat_uv_flag = 1;
        #10;
        show_status("TEST3: bat_uv_flag=1 (EXPECT 1)");
        bat_uv_flag = 0;

        // ---------------------------------------------
        // TEST 4: Fast failure - thermal trip
        // ---------------------------------------------
        thermal_trip = 1;
        #10;
        show_status("TEST4: thermal_trip=1 (EXPECT 1)");
        thermal_trip = 0;

        // ---------------------------------------------
        // TEST 5: Fast failure - comm timeout
        // ---------------------------------------------
        comm_timeout = 1;
        #10;
        show_status("TEST5: comm_timeout=1 (EXPECT 1)");
        comm_timeout = 0;

        // ---------------------------------------------
        // TEST 6: Multiple fast failures
        // ---------------------------------------------
        bat_uv_flag = 1;
        thermal_trip = 1;
        #10;
        show_status("TEST6: multiple fast failures (EXPECT 1)");
        bat_uv_flag = 0;
        thermal_trip = 0;

        // ---------------------------------------------
        // TEST 7: Temperature below MIN → clamp
        // ---------------------------------------------
        avg_temperature = 12'sd0;
        bat_soc = 8'd200;
        bat_soh = 8'd200;
        link_quality = 8'd200;

        #20;
        show_status("TEST7: temp below MIN (EXPECT 0)");

        // ---------------------------------------------
        // TEST 8: Temperature above MAX → clamp
        // ---------------------------------------------
        avg_temperature = 12'sd4000;
        #20;
        show_status("TEST8: temp above MAX");

        // ---------------------------------------------
        // TEST 9: Force score below RED threshold
        // ---------------------------------------------
        bat_soc = 8'd40;
        bat_soh = 8'd50;
        link_quality = 8'd40;
        avg_temperature = 12'sd2560;

        #20;
        show_status("TEST9: score < RED (EXPECT 1)");

        // ---------------------------------------------
        // TEST 10: Recovery
        // ---------------------------------------------
        bat_soc = 8'd240;
        bat_soh = 8'd240;
        link_quality = 8'd240;
        avg_temperature = 12'sd1280;

        #20;
        show_status("TEST10: recovered health (EXPECT 0)");

        $display("========================================");
        $display(" TEST COMPLETE");
        $display("========================================");
        $finish;
    end

endmodule

Queen Successor Trigger Unit - QSTU/Queen Successor Trigger Unit - QSTU.sim/sim_1/behav/xsim/simulation.vcd
$date
   Wed Jan  7 19:46:32 2026
$end

$version
  2025.1.0
  $dumpfile ("simulation.vcd") 
$end

$timescale
  1ps
$end

$scope module qstu_tb $end
$var reg 1 ! clk $end
$var reg 1 " rst_n $end
$var reg 1 # flight_stable $end
$var reg 8 $ bat_soc [7:0] $end
$var reg 8 % bat_soh [7:0] $end
$var reg 12 & avg_temperature [11:0] $end
$var reg 8 ' link_quality [7:0] $end
$var reg 1 ( bat_uv_flag $end
$var reg 1 ) thermal_trip $end
$var reg 1 * comm_timeout $end
$var reg 1 + elec_trigger $end
$scope module dut $end
$var wire 1 , clk $end
$var wire 1 - rst_n $end
$var wire 1 . flight_stable $end
$var wire 8 / bat_soc [7:0] $end
$var wire 8 0 bat_soh [7:0] $end
$var wire 12 1 avg_temperature [11:0] $end
$var wire 8 2 link_quality [7:0] $end
$var wire 1 3 bat_uv_flag $end
$var wire 1 4 thermal_trip $end
$var wire 1 5 comm_timeout $end
$var reg 1 + elec_trigger $end
$var reg 12 6 clmp_temp [11:0] $end
$var reg 32 7 temp_mult [31:0] $end
$var reg 16 8 temp_health [15:0] $end
$var reg 32 9 soc_mult [31:0] $end
$var reg 32 : soh_mult [31:0] $end
$var reg 32 ; temp_h_mult [31:0] $end
$var reg 32 < link_mult [31:0] $end
$var reg 32 = score_accum [31:0] $end
$var reg 16 > health_score [15:0] $end
$var reg 1 ? fast_failure $end
$upscope $end
$scope task reset_dut $end
$upscope $end
$scope task show_status $end
$upscope $end
$upscope $end
$enddefinitions $end

#0
$dumpvars
0!
0"
0#
b0 $
b0 %
b0 &
b0 '
0(
0)
0*
0+
0,
0-
0.
b0 /
b0 0
b0 1
b0 2
03
04
05
b1010000000 6
b11111111111110101010101100000000 7
b0 8
b0 9
b0 :
b0 ;
b0 <
b0 =
b0 >
0?
$end

#5000
1!
1,

#10000
0!
0,

#15000
1!
1,

#20000
0!
1"
0,
1-

#25000
1!
1,

#30000
0!
b11111111 $
b11111111 %
b10100000000 &
b11111111 '
0,
b11111111 /
b11111111 0
b10100000000 1
b11111111 2
b10100000000 6
b11111111111101010101011000000000 7
b101010101011010 8
b111111110000000000000 9
b111111110000000000000 :
b1010101010110100000000000000 ;
b111111110000000000000 <
b111010011110110 =
b111010011110110 >

#35000
1!
1,

#40000
0!
0,

#45000
1!
1,

#50000
0!
1#
b11100110 $
b11110000 %
b11011100 '
0,
1.
b11100110 /
b11110000 0
b11011100 2
b111001100000000000000 9
b111100000000000000000 :
b110111000000000000000 <
b110101110010110 =
b110101110010110 >

#55000
1!
1,

#60000
0!
0,

#65000
1!
1,

#70000
0!
1(
1+
0,
13
1?

#75000
1!
1,

#80000
0!
0(
1)
0,
03
14

#85000
1!
1,

#90000
0!
0)
1*
0,
04
15

#95000
1!
1,

#100000
0!
1(
1)
0*
0,
13
14
05

#105000
1!
1,

#110000
0!
b11001000 $
b11001000 %
b0 &
b11001000 '
0(
0)
0+
0,
b11001000 /
b11001000 0
b0 1
b11001000 2
03
04
b1010000000 6
b11111111111110101010101100000000 7
b0 8
b110010000000000000000 9
b110010000000000000000 :
b0 ;
b110010000000000000000 <
b100101100000000 =
b100101100000000 >
0?

#115000
1!
1,

#120000
0!
0,

#125000
1!
1,

#130000
0!
b111110100000 &
0,
b111110100000 1

#135000
1!
1,

#140000
0!
0,

#145000
1!
1,

#150000
0!
b101000 $
b110010 %
b101000000000 &
b101000 '
1+
0,
b101000 /
b110010 0
b101000000000 1
b101000 2
b1010000000000000000 9
b1100100000000000000 :
b1010000000000000000 <
b1000001000000 =
b1000001000000 >

#155000
1!
1,

#160000
0!
0,

#165000
1!
1,

#170000
0!
b11110000 $
b11110000 %
b10100000000 &
b11110000 '
0+
0,
b11110000 /
b11110000 0
b10100000000 1
b11110000 2
b10100000000 6
b11111111111101010101011000000000 7
b101010101011010 8
b111100000000000000000 9
b111100000000000000000 :
b1010101010110100000000000000 ;
b111100000000000000000 <
b110111101010110 =
b110111101010110 >

