qstuV2/qstuV2.srcs/sources_1/new/qstu_config.vh
// Contains common parameter definitions for the QSTU subsystem.

`ifndef QSTU_DEFS_VH
`define QSTU_DEFS_VH

// Data widths for sensor and status inputs
`define HEALTH_PARAM_WIDTH   8
`define TEMP_WIDTH          12

// Data widths for configuration parameters
`define WEIGHT_WIDTH        16
`define THRESHOLD_WIDTH     16
`define TEMP_LIMIT_WIDTH    13

// Internal calculation precision
`define SCORE_WIDTH         16
`define MULT_WIDTH          32
`define ACCUM_WIDTH         32

`endif // QSTU_DEFS_VH

qstuV2/qstuV2.srcs/sources_1/new/qstu_trigger.v
// qstu_trigger.v
//
// This module contains the sequential (registered) logic for the QSTU.
// It latches the health score when appropriate and generates the final,
// stable trigger output.

`include "qstu_config.vh"

module qstu_trigger (
    input                                   clk,
    input                                   rst_n,

    // Inputs from Compute Module
    input signed [`SCORE_WIDTH-1:0]         health_score_next,
    input                                   fast_failure,
    input                                   slow_eval_en,

    // Inputs from Top-Level
    input                                   flight_stable,
    input signed [`THRESHOLD_WIDTH-1:0]     RED_BAND_THRESHOLD,

    // Final Output
    output reg                              elec_trigger
);

    reg signed [`SCORE_WIDTH-1:0] health_score_reg;

    // Registered Slow Path (stores health score only when needed)
    always @(posedge clk or negedge rst_n) begin
        if (!rst_n)
            health_score_reg <= 16'd0;
        else if (slow_eval_en)
            health_score_reg <= health_score_next;
    end

    // Registered Trigger (generates the final output)
    always @(posedge clk or negedge rst_n) begin
        if (!rst_n)
            elec_trigger <= 1'b0;
        else if (!flight_stable)
            elec_trigger <= 1'b0;
        else
            elec_trigger <= fast_failure |
                            (health_score_reg <= RED_BAND_THRESHOLD);
    end

endmodule

qstuV2/qstuV2.srcs/sources_1/new/qstu_compute.v
// qstu_compute.v
//
// This module contains the purely combinational logic for the QSTU.
// It calculates the drone's health score based on sensor inputs and
// dynamic configuration parameters.

`include "qstu_config.vh"

module qstu_compute (
    // Sensor and Status Inputs
    input                                   flight_stable,
    input       [`HEALTH_PARAM_WIDTH-1:0]   bat_soc,
    input       [`HEALTH_PARAM_WIDTH-1:0]   bat_soh,
    input signed [`TEMP_WIDTH-1:0]          avg_temperature,
    input       [`HEALTH_PARAM_WIDTH-1:0]   link_quality,
    input                                   bat_uv_flag,
    input                                   thermal_trip,
    input                                   comm_timeout,

    // Configuration Inputs (from top-level)
    input signed [`TEMP_LIMIT_WIDTH-1:0]    TEMP_MIN_Q,
    input signed [`TEMP_LIMIT_WIDTH-1:0]    TEMP_MAX_Q,
    input signed [`WEIGHT_WIDTH-1:0]        TEMP_C1,
    input signed [`WEIGHT_WIDTH-1:0]        TEMP_C2,
    input signed [`WEIGHT_WIDTH-1:0]        W_SOC,
    input signed [`WEIGHT_WIDTH-1:0]        W_SOH,
    input signed [`WEIGHT_WIDTH-1:0]        W_TEMP,
    input signed [`WEIGHT_WIDTH-1:0]        W_LINK,

    // Outputs to the trigger logic module
    output reg signed [`SCORE_WIDTH-1:0]    health_score_next,
    output                                  fast_failure,
    output                                  slow_eval_en
);

    // --- Internal Combinational Signals ---
    reg signed [`TEMP_WIDTH-1:0]      clmp_temp;
    reg signed [`MULT_WIDTH-1:0]      temp_mult;
    reg signed [`SCORE_WIDTH-1:0]     temp_health_next;
    reg signed [`MULT_WIDTH-1:0]      soc_mult, soh_mult, temp_h_mult, link_mult;
    reg signed [`ACCUM_WIDTH-1:0]      score_accum;

    // --- Fast Failure and Slow Path Enable Logic ---
    assign fast_failure = bat_uv_flag | thermal_trip | comm_timeout;
    assign slow_eval_en = flight_stable & ~fast_failure;

    // --- Combinational Logic Blocks ---
    always @(*) begin
        // 1. Temperature Clamp
        if (avg_temperature < TEMP_MIN_Q)
            clmp_temp = TEMP_MIN_Q;
        else if (avg_temperature > TEMP_MAX_Q)
            clmp_temp = TEMP_MAX_Q;
        else
            clmp_temp = avg_temperature;

        // 2. Temperature Health Calculation (Affine)
        temp_mult = clmp_temp * TEMP_C1;
        temp_health_next = (temp_mult >> 5) + TEMP_C2; // Align to Q1.15

        if (temp_health_next < 0)
            temp_health_next = 16'd0;
        else if (temp_health_next > 16'h7FFF)
            temp_health_next = 16'h7FFF;

        // 3. Final Health Score Calculation
        soc_mult    = bat_soc       * W_SOC;
        soh_mult    = bat_soh       * W_SOH;
        temp_h_mult = temp_health_next * W_TEMP;
        link_mult   = link_quality * W_LINK;

        score_accum =
              (soc_mult    >> 8)
            + (soh_mult    >> 8)
            + (temp_h_mult >> 15)
            + (link_mult   >> 8);

        if (score_accum < 0)
            health_score_next = 16'd0;
        else if (score_accum > 16'h7FFF)
            health_score_next = 16'h7FFF;
        else
            health_score_next = score_accum[`SCORE_WIDTH-1:0];
    end

endmodule

qstuV2/qstuV2.srcs/sources_1/new/qstu_subsystem.v
// qstu_subsystem.v
//
// Top-level wrapper for the hierarchical Queen Successor Trigger Unit.
// This module instantiates the compute and trigger sub-modules.
// Configuration parameters are provided as inputs to this wrapper.

`include "qstu_config.vh"

module qstu_subsystem (
    input                                   clk,
    input                                   rst_n,

    // Sensor and Status Inputs
    input                                   flight_stable,
    input       [`HEALTH_PARAM_WIDTH-1:0]   bat_soc,
    input       [`HEALTH_PARAM_WIDTH-1:0]   bat_soh,
    input signed [`TEMP_WIDTH-1:0]          avg_temperature,
    input       [`HEALTH_PARAM_WIDTH-1:0]   link_quality,
    input                                   bat_uv_flag,
    input                                   thermal_trip,
    input                                   comm_timeout,

    // Runtime Configuration Inputs
    input signed [`TEMP_LIMIT_WIDTH-1:0]    cfg_temp_min_q,
    input signed [`TEMP_LIMIT_WIDTH-1:0]    cfg_temp_max_q,
    input signed [`WEIGHT_WIDTH-1:0]        cfg_temp_c1,
    input signed [`WEIGHT_WIDTH-1:0]        cfg_temp_c2,
    input signed [`WEIGHT_WIDTH-1:0]        cfg_w_soc,
    input signed [`WEIGHT_WIDTH-1:0]        cfg_w_soh,
    input signed [`WEIGHT_WIDTH-1:0]        cfg_w_temp,
    input signed [`WEIGHT_WIDTH-1:0]        cfg_w_link,
    input signed [`THRESHOLD_WIDTH-1:0]     cfg_red_band_threshold,

    // Final Trigger Output
    output                                  elec_trigger
);

    // --- Internal wires to connect sub-modules ---
    wire signed [`SCORE_WIDTH-1:0]    w_health_score_next;
    wire                              w_fast_failure;
    wire                              w_slow_eval_en;

    // Instantiate the Combinational Compute Block
    qstu_compute compute_unit (
        .flight_stable      (flight_stable),
        .bat_soc            (bat_soc),
        .bat_soh            (bat_soh),
        .avg_temperature    (avg_temperature),
        .link_quality       (link_quality),
        .bat_uv_flag        (bat_uv_flag),
        .thermal_trip       (thermal_trip),
        .comm_timeout       (comm_timeout),

        .TEMP_MIN_Q         (cfg_temp_min_q),
        .TEMP_MAX_Q         (cfg_temp_max_q),
        .TEMP_C1            (cfg_temp_c1),
        .TEMP_C2            (cfg_temp_c2),
        .W_SOC              (cfg_w_soc),
        .W_SOH              (cfg_w_soh),
        .W_TEMP             (cfg_w_temp),
        .W_LINK             (cfg_w_link),

        .health_score_next  (w_health_score_next),
        .fast_failure       (w_fast_failure),
        .slow_eval_en       (w_slow_eval_en)
    );

    // Instantiate the Sequential Trigger Block
    qstu_trigger trigger_unit (
        .clk                (clk),
        .rst_n              (rst_n),

        .health_score_next  (w_health_score_next),
        .fast_failure       (w_fast_failure),
        .slow_eval_en       (w_slow_eval_en),

        .flight_stable      (flight_stable),
        .RED_BAND_THRESHOLD (cfg_red_band_threshold),

        .elec_trigger       (elec_trigger)
    );

endmodule

qstuV2/qstuV2.srcs/sim_1/new/qstu_subsystem_tb.v
`timescale 1ns/1ps

`include "qstu_config.vh"

module qstu_subsystem_tb;

    reg                                   clk;
    reg                                   rst_n;

    reg                                   flight_stable;
    reg       [`HEALTH_PARAM_WIDTH-1:0]   bat_soc;
    reg       [`HEALTH_PARAM_WIDTH-1:0]   bat_soh;
    reg signed [`TEMP_WIDTH-1:0]          avg_temperature;
    reg       [`HEALTH_PARAM_WIDTH-1:0]   link_quality;
    reg                                   bat_uv_flag;
    reg                                   thermal_trip;
    reg                                   comm_timeout;

    reg signed [`TEMP_LIMIT_WIDTH-1:0]    cfg_temp_min_q;
    reg signed [`TEMP_LIMIT_WIDTH-1:0]    cfg_temp_max_q;
    reg signed [`WEIGHT_WIDTH-1:0]        cfg_temp_c1;
    reg signed [`WEIGHT_WIDTH-1:0]        cfg_temp_c2;
    reg signed [`WEIGHT_WIDTH-1:0]        cfg_w_soc;
    reg signed [`WEIGHT_WIDTH-1:0]        cfg_w_soh;
    reg signed [`WEIGHT_WIDTH-1:0]        cfg_w_temp;
    reg signed [`WEIGHT_WIDTH-1:0]        cfg_w_link;
    reg signed [`THRESHOLD_WIDTH-1:0]     cfg_red_band_threshold;

    wire                                  elec_trigger;

    localparam signed [12:0] P_TEMP_MIN_Q = 13'sd640;
    localparam signed [12:0] P_TEMP_MAX_Q = 13'sd2560;
    localparam signed [15:0] P_TEMP_C1 = -16'sd546;
    localparam signed [15:0] P_TEMP_C2 =  16'sd43690;
    localparam signed [15:0] P_W_SOC  = 16'sd8192;
    localparam signed [15:0] P_W_SOH  = 16'sd8192;
    localparam signed [15:0] P_W_TEMP = 16'sd8192;
    localparam signed [15:0] P_W_LINK = 16'sd8192;
    localparam signed [15:0] P_RED_BAND_THRESHOLD = 16'sd9830;

    qstu_subsystem dut (
        .clk(clk),
        .rst_n(rst_n),
        .flight_stable(flight_stable),
        .bat_soc(bat_soc),
        .bat_soh(bat_soh),
        .avg_temperature(avg_temperature),
        .link_quality(link_quality),
        .bat_uv_flag(bat_uv_flag),
        .thermal_trip(thermal_trip),
        .comm_timeout(comm_timeout),
        .cfg_temp_min_q(cfg_temp_min_q),
        .cfg_temp_max_q(cfg_temp_max_q),
        .cfg_temp_c1(cfg_temp_c1),
        .cfg_temp_c2(cfg_temp_c2),
        .cfg_w_soc(cfg_w_soc),
        .cfg_w_soh(cfg_w_soh),
        .cfg_w_temp(cfg_w_temp),
        .cfg_w_link(cfg_w_link),
        .cfg_red_band_threshold(cfg_red_band_threshold),
        .elec_trigger(elec_trigger)
    );

    always #5 clk = ~clk;

    task reset_and_config_dut;
    begin
        clk = 0;
        rst_n = 0;
        flight_stable = 0;
        bat_soc = 0;
        bat_soh = 0;
        avg_temperature = 0;
        link_quality = 0;
        bat_uv_flag = 0;
        thermal_trip = 0;
        comm_timeout = 0;

        cfg_temp_min_q = P_TEMP_MIN_Q;
        cfg_temp_max_q = P_TEMP_MAX_Q;
        cfg_temp_c1 = P_TEMP_C1;
        cfg_temp_c2 = P_TEMP_C2;
        cfg_w_soc = P_W_SOC;
        cfg_w_soh = P_W_SOH;
        cfg_w_temp = P_W_TEMP;
        cfg_w_link = P_W_LINK;
        cfg_red_band_threshold = P_RED_BAND_THRESHOLD;

        #20;
        rst_n = 1;
        #10;
    end
    endtask

    initial begin
        $display("\n======================================================");
        $display("     STARTING QSTU SUBSYSTEM TESTBENCH");
        $display("======================================================");

        $dumpfile("simulation.vcd");
        $dumpvars(0, qstu_subsystem_tb);

        reset_and_config_dut();

        bat_soc = 8'd255;
        bat_soh = 8'd255;
        link_quality = 8'd255;
        avg_temperature = 12'sd1280;
        flight_stable = 0;
        #20;
        $display("[%0t ns] TEST  1: Flight stable    (EXPECT 0) -> TRIGGER = %0d", $time, elec_trigger);

        flight_stable = 1;
        bat_soc = 8'd230;
        bat_soh = 8'd240;
        link_quality = 8'd220;
        avg_temperature = 12'sd1280;
        #20;
        $display("[%0t ns] TEST  2: Healthy system       (EXPECT 0) -> TRIGGER = %0d", $time, elec_trigger);

        bat_uv_flag = 1;
        #10;
        $display("[%0t ns] TEST  3: Fast Fail - UV Flag   (EXPECT 1) -> TRIGGER = %0d", $time, elec_trigger);
        bat_uv_flag = 0;
        #10;

        thermal_trip = 1;
        #10;
        $display("[%0t ns] TEST  4: Fast Fail - Thermal  (EXPECT 1) -> TRIGGER = %0d", $time, elec_trigger);
        thermal_trip = 0;
        #10;

        comm_timeout = 1;
        #10;
        $display("[%0t ns] TEST  5: Fast Fail - Comm     (EXPECT 1) -> TRIGGER = %0d", $time, elec_trigger);
        comm_timeout = 0;
        #10;

        bat_uv_flag = 1;
        thermal_trip = 1;
        #10;
        $display("[%0t ns] TEST  6: Multiple Fast Fails  (EXPECT 1) -> TRIGGER = %0d", $time, elec_trigger);
        bat_uv_flag = 0;
        thermal_trip = 0;
        #10;

        avg_temperature = 12'sd0;
        bat_soc = 8'd200;
        bat_soh = 8'd200;
        link_quality = 8'd200;
        #20;
        $display("[%0t ns] TEST  7: Temp below MIN clamp (EXPECT 0) -> TRIGGER = %0d", $time, elec_trigger);

        avg_temperature = 12'sd4000;
        #20;
        $display("[%0t ns] TEST  8: Temp above MAX clamp (EXPECT 0) -> TRIGGER = %0d", $time, elec_trigger);

        bat_soc = 8'd40;
        bat_soh = 8'd50;
        link_quality = 8'd40;
        avg_temperature = 12'sd2560;
        #20;
        $display("[%0t ns] TEST  9: Score below RED      (EXPECT 1) -> TRIGGER = %0d", $time, elec_trigger);

        bat_soc = 8'd240;
        bat_soh = 8'd240;
        link_quality = 8'd240;
        avg_temperature = 12'sd1280;
        #20;
        $display("[%0t ns] TEST 10: Health recovered     (EXPECT 0) -> TRIGGER = %0d", $time, elec_trigger);

        $display("\n======================================================");
        $display("              TESTBENCH COMPLETE");
        $display("======================================================");
        $finish;
    end

endmodule

qstuV2/qstuV2.sim/sim_1/behav/simulation.vcd
$date
   Thu Feb 05 11:59:55 2026
$end
$version
  2016.4
$end
$timescale
  1ps
$end
$scope module qstu_subsystem_tb $end
$var reg 1 ! clk $end
$var reg 1 " rst_n $end
$var reg 1 # flight_stable $end
$var reg 8 $ bat_soc [7:0] $end
$var reg 8 % bat_soh [7:0] $end
$var reg 12 & avg_temperature [11:0] $end
$var reg 8 ' link_quality [7:0] $end
$var reg 1 ( bat_uv_flag $end
$var reg 1 ) thermal_trip $end
$var reg 1 * comm_timeout $end
$var reg 13 + cfg_temp_min_q [12:0] $end
$var reg 13 , cfg_temp_max_q [12:0] $end
$var reg 16 - cfg_temp_c1 [15:0] $end
$var reg 16 . cfg_temp_c2 [15:0] $end
$var reg 16 / cfg_w_soc [15:0] $end
$var reg 16 0 cfg_w_soh [15:0] $end
$var reg 16 1 cfg_w_temp [15:0] $end
$var reg 16 2 cfg_w_link [15:0] $end
$var reg 16 3 cfg_red_band_threshold [15:0] $end
$var wire 1 4 elec_trigger $end
$var parameter 13 5 P_TEMP_MIN_Q [12:0] $end
$var parameter 13 6 P_TEMP_MAX_Q [12:0] $end
$var parameter 16 7 P_TEMP_C1 [15:0] $end
$var parameter 16 8 P_TEMP_C2 [15:0] $end
$var parameter 16 9 P_W_SOC [15:0] $end
$var parameter 16 : P_W_SOH [15:0] $end
$var parameter 16 ; P_W_TEMP [15:0] $end
$var parameter 16 < P_W_LINK [15:0] $end
$var parameter 16 = P_RED_BAND_THRESHOLD [15:0] $end
$scope module dut $end
$var wire 1 > clk $end
$var wire 1 ? rst_n $end
$var wire 1 @ flight_stable $end
$var wire 8 A bat_soc [7:0] $end
$var wire 8 B bat_soh [7:0] $end
$var wire 12 C avg_temperature [11:0] $end
$var wire 8 D link_quality [7:0] $end
$var wire 1 E bat_uv_flag $end
$var wire 1 F thermal_trip $end
$var wire 1 G comm_timeout $end
$var wire 13 H cfg_temp_min_q [12:0] $end
$var wire 13 I cfg_temp_max_q [12:0] $end
$var wire 16 J cfg_temp_c1 [15:0] $end
$var wire 16 K cfg_temp_c2 [15:0] $end
$var wire 16 L cfg_w_soc [15:0] $end
$var wire 16 M cfg_w_soh [15:0] $end
$var wire 16 N cfg_w_temp [15:0] $end
$var wire 16 O cfg_w_link [15:0] $end
$var wire 16 P cfg_red_band_threshold [15:0] $end
$var wire 1 4 elec_trigger $end
$var wire 16 Q w_health_score_next [15:0] $end
$var wire 1 R w_fast_failure $end
$var wire 1 S w_slow_eval_en $end
$scope module compute_unit $end
$var wire 1 @ flight_stable $end
$var wire 8 A bat_soc [7:0] $end
$var wire 8 B bat_soh [7:0] $end
$var wire 12 C avg_temperature [11:0] $end
$var wire 8 D link_quality [7:0] $end
$var wire 1 E bat_uv_flag $end
$var wire 1 F thermal_trip $end
$var wire 1 G comm_timeout $end
$var wire 13 H TEMP_MIN_Q [12:0] $end
$var wire 13 I TEMP_MAX_Q [12:0] $end
$var wire 16 J TEMP_C1 [15:0] $end
$var wire 16 K TEMP_C2 [15:0] $end
$var wire 16 L W_SOC [15:0] $end
$var wire 16 M W_SOH [15:0] $end
$var wire 16 N W_TEMP [15:0] $end
$var wire 16 O W_LINK [15:0] $end
$var reg 16 T health_score_next [15:0] $end
$var wire 1 R fast_failure $end
$var wire 1 S slow_eval_en $end
$var reg 12 U clmp_temp [11:0] $end
$var reg 32 V temp_mult [31:0] $end
$var reg 16 W temp_health_next [15:0] $end
$var reg 32 X soc_mult [31:0] $end
$var reg 32 Y soh_mult [31:0] $end
$var reg 32 Z temp_h_mult [31:0] $end
$var reg 32 [ link_mult [31:0] $end
$var reg 32 \ score_accum [31:0] $end
$upscope $end
$scope module trigger_unit $end
$var wire 1 > clk $end
$var wire 1 ? rst_n $end
$var wire 16 Q health_score_next [15:0] $end
$var wire 1 R fast_failure $end
$var wire 1 S slow_eval_en $end
$var wire 1 @ flight_stable $end
$var wire 16 P RED_BAND_THRESHOLD [15:0] $end
$var reg 1 ] elec_trigger $end
$var reg 16 ^ health_score_reg [15:0] $end
$upscope $end
$upscope $end
$scope task reset_and_config_dut $end
$upscope $end
$upscope $end
$enddefinitions $end
#0
$dumpvars
0!
0"
0#
b0 $
b0 %
b0 &
b0 '
0(
0)
0*
b1010000000 +
b101000000000 ,
b1111110111011110 -
b1010101010101010 .
b10000000000000 /
b10000000000000 0
b10000000000000 1
b10000000000000 2
b10011001100110 3
04
b1010000000 5
b101000000000 6
b1111110111011110 7
b1010101010101010 8
b10000000000000 9
b10000000000000 :
b10000000000000 ;
b10000000000000 <
b10011001100110 =
0>
0?
0@
b0 A
b0 B
b0 C
b0 D
0E
0F
0G
b1010000000 H
b101000000000 I
b1111110111011110 J
b1010101010101010 K
b10000000000000 L
b10000000000000 M
b10000000000000 N
b10000000000000 O
b10011001100110 P
b0 Q
0R
0S
b0 T
b1010000000 U
b11111111111110101010101100000000 V
b0 W
b0 X
b0 Y
b0 Z
b0 [
b0 \
0]
b0 ^
$end
#5000
1!
1>
0]
#10000
0!
0>
#15000
1!
1>
0]
#20000
0!
1"
0>
1?
#25000
1!
1>
0]
#30000
0!
b11111111 $
b11111111 %
b10100000000 &
b11111111 '
0>
b11111111 A
b11111111 B
b10100000000 C
b11111111 D
b111010011110110 Q
b111010011110110 T
b10100000000 U
b11111111111101010101011000000000 V
b101010101011010 W
b111111110000000000000 X
b111111110000000000000 Y
b1010101010110100000000000000 Z
b111111110000000000000 [
b111010011110110 \
#35000
1!
1>
0]
#40000
0!
0>
#45000
1!
1>
0]
#50000
0!
1#
b11100110 $
b11110000 %
b10100000000 &
b11011100 '
0>
1@
b11100110 A
b11110000 B
b11011100 D
b110101110010110 Q
1S
b110101110010110 T
b10100000000 U
b11111111111101010101011000000000 V
b101010101011010 W
b111001100000000000000 X
b111100000000000000000 Y
b1010101010110100000000000000 Z
b110111000000000000000 [
b110101110010110 \
#55000
1!
14
1>
1]
b110101110010110 ^
#60000
0!
0>
#65000
1!
04
1>
0]
#70000
0!
1(
0>
1E
1R
0S
#75000
1!
14
1>
1]
#80000
0!
0(
0>
0E
0R
1S
#85000
1!
04
1>
0]
#90000
0!
1)
0>
1F
1R
0S
#95000
1!
14
1>
1]
#100000
0!
0)
0>
0F
0R
1S
#105000
1!
04
1>
0]
#110000
0!
1*
0>
1G
1R
0S
#115000
1!
14
1>
1]
#120000
0!
0*
0>
0G
0R
1S
#125000
1!
04
1>
0]
#130000
0!
1(
1)
0>
1E
1F
1R
0S
#135000
1!
14
1>
1]
#140000
0!
0(
0)
0>
0E
0F
0R
1S
#145000
1!
04
1>
0]
#150000
0!
b11001000 $
b11001000 %
b0 &
b11001000 '
0>
b11001000 A
b11001000 B
b0 C
b11001000 D
b100101100000000 Q
b100101100000000 T
b1010000000 U
b11111111111110101010101100000000 V
b0 W
b110010000000000000000 X
b110010000000000000000 Y
b0 Z
b110010000000000000000 [
b100101100000000 \
#155000
1!
1>
0]
b100101100000000 ^
#160000
0!
0>
#165000
1!
1>
0]
#170000
0!
b111110100000 &
0>
b111110100000 C
b100101100000000 T
b1010000000 U
b11111111111110101010101100000000 V
b0 W
b110010000000000000000 X
b110010000000000000000 Y
b0 Z
b110010000000000000000 [
b100101100000000 \
#175000
1!
1>
0]
#180000
0!
0>
#185000
1!
1>
0]
#190000
0!
b101000 $
b110010 %
b101000000000 &
b101000 '
0>
b101000 A
b110010 B
b101000000000 C
b101000 D
b1000001000000 Q
b1000001000000 T
b1010000000 U
b11111111111110101010101100000000 V
b0 W
b1010000000000000000 X
b1100100000000000000 Y
b0 Z
b1010000000000000000 [
b1000001000000 \
#195000
1!
1>
0]
b1000001000000 ^
#200000
0!
0>
#205000
1!
14
1>
1]
#210000
0!
b11110000 $
b11110000 %
b10100000000 &
b11110000 '
0>
b11110000 A
b11110000 B
b10100000000 C
b11110000 D
b110111101010110 Q
b110111101010110 T
b10100000000 U
b11111111111101010101011000000000 V
b101010101011010 W
b111100000000000000000 X
b111100000000000000000 Y
b1010101010110100000000000000 Z
b111100000000000000000 [
b110111101010110 \
#215000
1!
1>
1]
b110111101010110 ^
#220000
0!
0>
#225000
1!
04
1>
0]
